{
  "$sys":{
    "guid":"88b9280f-7cce-7739-1e65-a883371cd498",
    "typeGuid":"7f93991a-4da9-4892-79c2-35fe44e69083"
  },
  "fields":{
    "Id":1456,
    "Name":"MainForm"
  },
  "collections": {
    "Params": [
      {
        "$sys": {
          "guid": "a188cfcf-f2de-dc88-f51d-0f42a7e745a1",
          "typeGuid": "4943ce3e-a6cb-65f7-8805-ec339555a981"
        },
        "fields": {
          "Id": 1457,
          "Name": "FormParam1",
          "Type": "param",
          "Kind": "out",
          "Value": ""
        },
        "collections": {}
      }
    ],
    "Children": [
      {
        "$sys": {
          "guid": "15e8110a-1453-725a-c443-c63f9f10ef6a",
          "typeGuid": "1d95ab61-df00-aec8-eff5-0f90187891cf"
        },
        "fields": {
          "Id": 11,
          "Name": "MainContainer"
        },
        "collections": {
          "Children": [
            {
              "$sys": {
                "guid": "f0ee9df0-314c-e22c-4c6e-64e76f65bb2d",
                "typeGuid": "5e89f6c7-ccc2-a850-2f67-b5f5f20c3d47"
              },
              "fields": {
                "Id": 127,
                "Name": "DataModel"
              },
              "collections": {
                "Datasets": [
                  {
                    "$sys": {
                      "guid": "061b1347-18a2-a829-fcce-ba59058b4bdf",
                      "typeGuid": "3f3341c7-2f06-8d9d-4099-1075c158aeee"
                    },
                    "fields": {
                      "Id": 122,
                      "Name": "DatasetCompany",
                      "Root": "ab573a02-b888-b3b4-36a7-38629a5fe6b7",
                      "Active": true,
                      "OnMoveCursor" : " { this.getControlMgr().getByName('FormParam1').value(newVal); } "
                    },
                    "collections": {
                    }
                  },
                  {
                    "$sys": {
                      "guid": "eefbcccf-743a-66a4-c3a2-4751d2a334f5",
                      "typeGuid": "3f3341c7-2f06-8d9d-4099-1075c158aeee"
                    },
                    "fields": {
                      "Id": 123,
                      "Name": "DatasetContact",
                      "Root": "b49d39c9-b903-cccd-7d32-b84beb1b76dc",
                      "Active": true,
                      "Master": "061b1347-18a2-a829-fcce-ba59058b4bdf"
                    },
                    "collections": {
                    }
                  },
                  {
                    "$sys": {
                      "guid": "e559320d-d80d-48f7-ed4e-0ac63587e606",
                      "typeGuid": "3f3341c7-2f06-8d9d-4099-1075c158aeee"
                    },
                    "fields": {
                      "Id": 125,
                      "Name": "DatasetContract",
                      "Root": "8583ee1d-6936-19da-5ef0-9025fb7d1d8d",
                      "Active": true,
                      "Master": "061b1347-18a2-a829-fcce-ba59058b4bdf"
                    },
                    "collections": {
                    }
                  },
                  {
                    "$sys": {
                      "guid": "92720532-a58f-68bb-6e5a-02b28239e312",
                      "typeGuid": "3f3341c7-2f06-8d9d-4099-1075c158aeee"
                    },
                    "fields": {
                      "Id": 226,
                      "Name": "DatasetAddress",
                      "Root": "edca46bc-3389-99a2-32c0-a59665fcb6a7",
                      "Active": true,
                      "Master": "eefbcccf-743a-66a4-c3a2-4751d2a334f5"
                    },
                    "collections": {
                    }
                  }
                ]
              }
            },
            {
              "$sys": {
                "guid": "6077a56c-d1c2-cea8-9bdc-ae796e54462e",
                "typeGuid": "ff7830e2-7add-e65e-7ddf-caba8992d6d8"
              },
              "fields": {
                "Id": 22,
                "Name": "DataGridCompany",
                "Top": "67",
                "Left": "10",
                "Width": 380,
                "Height": 120,
                "Dataset": "061b1347-18a2-a829-fcce-ba59058b4bdf"
              },
              "collections": {
              }
            },
            {
              "$sys": {
                "guid": "6a7cea85-dd15-d958-fffc-1f15e155fcdf",
                "typeGuid": "affff8b1-10b0-20a6-5bb5-a9d88334b48e"
              },
              "fields": {
                "Id": 320,
                "Name": "DataEditId",
                "Top": "200",
                "Left": "10",
                "Width": 100,
                "Height": 20,
                "Dataset": "061b1347-18a2-a829-fcce-ba59058b4bdf",
                "DataField": "Id"
              },
              "collections": {
              }
            },
            {
              "$sys": {
                "guid": "265802e9-d5d5-953c-2712-1f4d8fa0e948",
                "typeGuid": "affff8b1-10b0-20a6-5bb5-a9d88334b48e"
              },
              "fields": {
                "Id": 321,
                "Name": "DataEdit1",
                "Top": "230",
                "Left": "10",
                "Width": 100,
                "Height": 20,
                "Dataset": "061b1347-18a2-a829-fcce-ba59058b4bdf",
                "DataField": "Name"
              },
              "collections": {
              }
            },
            {
              "$sys": {
                "guid": "dd28f133-8a15-1212-eb7b-1ebd8dfaaa4d",
                "typeGuid": "affff8b1-10b0-20a6-5bb5-a9d88334b48e"
              },
              "fields": {
                "Id": 322,
                "Name": "DataEditCountry",
                "Top": "260",
                "Left": "10",
                "Width": 100,
                "Height": 20,
                "Dataset": "061b1347-18a2-a829-fcce-ba59058b4bdf",
                "DataField": "country"
              },
              "collections": {
              }
            },
            {
              "$sys": {
                "guid": "a0a48c6f-0b42-ad7e-2008-799292f85595",
                "typeGuid": "affff8b1-10b0-20a6-5bb5-a9d88334b48e"
              },
              "fields": {
                "Id": 322,
                "Name": "DataEditCity",
                "Top": "290",
                "Left": "10",
                "Width": 100,
                "Height": 20,
                "Dataset": "061b1347-18a2-a829-fcce-ba59058b4bdf",
                "DataField": "city"
              },
              "collections": {
              }
            },
            {
              "$sys": {
                "guid": "95384974-2a8f-ddaa-2f47-d8b55cc3774f",
                "typeGuid": "affff8b1-10b0-20a6-5bb5-a9d88334b48e"
              },
              "fields": {
                "Id": 322,
                "Name": "DataEditAddress",
                "Top": "320",
                "Left": "10",
                "Width": 100,
                "Height": 20,
                "Dataset": "061b1347-18a2-a829-fcce-ba59058b4bdf",
                "DataField": "address"
              },
              "collections": {
              }
            },
            {
              "$sys": {
                "guid": "af9d1e98-73a6-4b35-b91c-edd498a749fc",
                "typeGuid": "ff7830e2-7add-e65e-7ddf-caba8992d6d8"
              },
              "fields": {
                "Id": 24,
                "Name": "DataGridContact",
                "Top": "67",
                "Left": "390",
                "Width": 660,
                "Height": 120,
                "Dataset": "eefbcccf-743a-66a4-c3a2-4751d2a334f5"
              },
              "collections": {
              }
            },
            {
              "$sys": {
                "guid": "b35fc71e-7216-f2a2-d222-a88f8f53ccea",
                "typeGuid": "a0e02c45-1600-6258-b17a-30a56301d7f1"
              },
              "fields": {
                "Id": 44,
                "Name": "PropEditor",
                "Top": "193",
                "Left": "1055"
              },
              "collections": {
              }
            },
            {
              "$sys": {
                "guid": "996934a2-7b67-b6a4-a01c-398ee08709bb",
                "typeGuid": "38aec981-30ae-ec1d-8f8f-5004958b4cfa"
              },
              "fields": {
                "Id": 55,
                "Name": "DbNavigator",
                "Top": "520",
                "Left": "20",
                "Nlevels": 3,
                "RootElem": "fc13e2b8-3600-b537-f9e5-654b7418c156",
                "Level": 0
              },
              "collections": {
              }
            },
            {
              "$sys": {
                "guid": "b99e85e6-8774-2449-00c0-bcbce0128351",
                "typeGuid": "1d95ab61-df00-aec8-eff5-0f90187891cf"
              },
              "fields": {
                "Id": 100,
                "Name": "Container2",
                "Width": 500,
                "Height": 50,
                "Top": "5",
                "Left": "230"
              },
              "collections": {
                "Children": [
                  {
                    "$sys": {
                      "guid": "fd584e0d-4c97-098a-10ac-31b3efb69bd1",
                      "typeGuid": "af419748-7b25-1633-b0a9-d539cada8e0d"
                    },
                    "fields": {
                      "Id": 101,
                      "Name": "Button1",
                      "Top": "5",
                      "Left": "30",
                      "Caption": "Button1"
                    },
                    "collections": {
                    }
                  },
                  {
                    "$sys": {
                      "guid": "7ca91e81-fbbc-d4ec-adcb-d69e059023b8",
                      "typeGuid": "af419748-7b25-1633-b0a9-d539cada8e0d"
                    },
                    "fields": {
                      "Id": 101,
                      "Name": "Button2",
                      "Top": "5",
                      "Left": "130",
                      "Caption": "Button2"
                    },
                    "collections": {
                    }
                  },
                  {
                    "$sys": {
                      "guid": "155c7048-5b17-ffbd-f892-4ca467c1be5a",
                      "typeGuid": "1d95ab61-df00-aec8-eff5-0f90187891cf"
                    },
                    "fields": {
                      "Id": 100,
                      "Name": "Container3",
                      "Width": 220,
                      "Height": 50,
                      "Top": "5",
                      "Left": "230"
                    },
                    "collections": {
                      "Children": [
                        {
                          "$sys": {
                            "guid": "0099aeb1-4b52-bbe0-fce4-82c7d27b3667",
                            "typeGuid": "af419748-7b25-1633-b0a9-d539cada8e0d"
                          },
                          "fields": {
                            "Id": 103,
                            "Name": "Button3.1",
                            "Top": "5",
                            "Left": "30",
                            "Caption": "Button3.1"
                          },
                          "collections": {
                          }
                        },
                        {
                          "$sys": {
                            "guid": "c81cc218-f872-ba67-688c-c46e412a9b3e",
                            "typeGuid": "af419748-7b25-1633-b0a9-d539cada8e0d"
                          },
                          "fields": {
                            "Id": 104,
                            "Name": "Button3.2",
                            "Top": "5",
                            "Left": "130",
                            "Caption": "Button3.2"
                          },
                          "collections": {
                          }
                        }
                      ]
                    }
                  }
                ]
              }
            },
            {
              "$sys": {
                "guid": "d25f0f38-b0bd-d505-a332-f26f3c6cf8d5",
                "typeGuid": "ff7830e2-7add-e65e-7ddf-caba8992d6d8"
              },
              "fields": {
                "Id": 224,
                "Name": "DataGridContact2",
                "Top": "311",
                "Left": "390",
                "Width": 660,
                "Height": 120,
                "Dataset": ""
              },
              "collections": {
              }
            },
            {
              "$sys": {
                "guid": "2fa698ff-68c5-f8ed-fef4-e3e1db468229",
                "typeGuid": "ff7830e2-7add-e65e-7ddf-caba8992d6d8"
              },
              "fields": {
                "Id": 225,
                "Name": "DataGridContact",
                "Top": "189",
                "Left": "390",
                "Width": 660,
                "Height": 120,
                "Dataset": "e559320d-d80d-48f7-ed4e-0ac63587e606"
              },
              "collections": {
              }
            },
            {
              "$sys": {
                "guid": "5029499d-3a2d-e81f-1281-6a00cb779a59",
                "typeGuid": "ff7830e2-7add-e65e-7ddf-caba8992d6d8"
              },
              "fields": {
                "Id": 226,
                "Name": "DataGridAddress",
                "Top": "67",
                "Left": "1052",
                "Width": 450,
                "Height": 120,
                "Dataset": "92720532-a58f-68bb-6e5a-02b28239e312"
              },
              "collections": {
              }
            }
          ]
        }
      }
    ]
  }
}